icua/__init__.py
icua/config.py
icua/agent/__init__.py
icua/agent/actuator_acceptability.py
icua/agent/actuator_avatar.py
icua/agent/actuator_guidance.py
icua/agent/agent_guidance.py
icua/agent/avatar.py
icua/agent/sensor_acceptability.py
icua/agent/sensor_userinput.py
icua/environment/__init__.py
icua/environment/multitask_ambient.py
icua/environment/multitask_environment.py
icua/environment/task.py
icua/event/__init__.py
icua/event/event_avatar.py
icua/event/event_guidance.py
icua/event/event_task.py
icua/extras/__init__.py
icua/extras/analysis/__init__.py
icua/extras/analysis/event_log_parser.py
icua/extras/analysis/get.py
icua/extras/analysis/get_user_input.py
icua/extras/analysis/plot.py
icua/extras/analysis/stats.py
icua/extras/eyetracking/__init__.py
icua/extras/eyetracking/error.py
icua/extras/eyetracking/event.py
icua/extras/eyetracking/eyetrackerbase.py
icua/extras/eyetracking/filter.py
icua/extras/eyetracking/sensor.py
icua/extras/eyetracking/tobii.py
icua/extras/logging/__init__.py
icua/extras/logging/actuator_logging.py
icua/utils/__init__.py
icua/utils/_const.py
icua/utils/_dict.py
icua/utils/_error.py
icua/utils/_geom.py
icua/utils/_logging.py
icua/utils/_schedule.dep.py
icua/utils/_schedule.py
icua/utils/_task_loader.py
icua/utils/_timestat.py
icua-2.0.12.dist-info/LICENSE
icua-2.0.12.dist-info/METADATA
icua-2.0.12.dist-info/WHEEL
icua-2.0.12.dist-info/top_level.txt
icua-2.0.12.dist-info/RECORD
