Metadata-Version: 2.1
Name: icua
Version: 2.0.12
Summary: Integrated Cognitive User Assistance v2 - a platform supporting research in human attention guidance.
Author-email: Benedict Wilkins <benrjw@gmail.com>
License:                     GNU GENERAL PUBLIC LICENSE
Project-URL: Repository, https://github.com/dicelab-rhul/icua2
Requires-Python: >=3.10
License-File: LICENSE
Requires-Dist: star_ray>=0.0.8
Requires-Dist: star_ray_pygame>=0.0.11
Requires-Dist: pyfuncschedule>=0.1.0
Requires-Dist: loguru>=0.7.2
Provides-Extra: tobii
Requires-Dist: tobii_research>=1.11.0; extra == "tobii"
Provides-Extra: dev
Requires-Dist: pytest>=6.2.4; extra == "dev"
